{
  "leaderboard" : [
    {
      "group" : "SCIENCE",
      "id" : "1090302026SCID125",
      "last_updated" : "2026-02-08 20:46:22",
      "level" : "🏅 Achiever",
      "name" : "JARIN TASNIM MIM",
      "xp_points" : 3191
    },
    {
      "group" : "HUMANITIES",
      "id" : "1090302026HUMD145",
      "last_updated" : "2025-10-30 19:06:50",
      "level" : "🏅 Achiever",
      "name" : "TANJINA AKTER ",
      "xp_points" : 2678
    },
    {
      "group" : "SCIENCE",
      "id" : "1090302026SCID118",
      "last_updated" : "2025-10-29 19:30:57",
      "level" : "🏅 Achiever",
      "name" : "MARJAN SHATHI ",
      "xp_points" : 2509
    },
    {
      "group" : "HUMANITIES",
      "id" : "1147422026HUMD2166",
      "last_updated" : "2026-02-14 21:38:06",
      "level" : "🎯 Explorer",
      "name" : "PROTIMA SHIL",
      "xp_points" : 1675
    },
    {
      "group" : "OTHERS",
      "id" : "11467820261007",
      "last_updated" : "2026-01-31 11:50:20",
      "level" : "🎯 Explorer",
      "name" : "NUHSANAT TASNIA",
      "xp_points" : 1518
    },
    {
      "group" : "SCIENCE",
      "id" : "1090302026SCIM117",
      "last_updated" : "2025-11-03 09:10:11",
      "level" : "🎯 Explorer",
      "name" : "SADIA MEHNAJ",
      "xp_points" : 1384
    },
    {
      "group" : "HUMANITIES",
      "id" : "1146782026HUMM1131",
      "last_updated" : "2026-02-02 06:37:45",
      "level" : "🎯 Explorer",
      "name" : "RUPA MONDOL",
      "xp_points" : 1334
    },
    {
      "group" : "HUMANITIES",
      "id" : "1146782026HUMD1114",
      "last_updated" : "2026-02-02 07:00:46",
      "level" : "🎯 Explorer",
      "name" : "RINI ISLAM",
      "xp_points" : 1312
    },
    {
      "group" : "BUSINESS",
      "id" : "1090302026BUSM307",
      "last_updated" : "2026-01-31 16:14:56",
      "level" : "🎯 Explorer",
      "name" : "IRIN MONY ",
      "xp_points" : 1252
    },
    {
      "group" : "SCIENCE",
      "id" : "1090302026SCID110",
      "last_updated" : "2025-10-28 09:58:40",
      "level" : "🎯 Explorer",
      "name" : "SAMIA SULTANA PUSPO",
      "xp_points" : 1181
    },
    {
      "group" : "HUMANITIES",
      "id" : "1146782026HUMD1140",
      "last_updated" : "2026-01-03 14:48:54",
      "level" : "🎯 Explorer",
      "name" : "ESRAT JAHAN TOMA ",
      "xp_points" : 1151
    },
    {
      "group" : "SCIENCE",
      "id" : "1090302026SCID114",
      "last_updated" : "2025-10-30 17:55:11",
      "level" : "🎯 Explorer",
      "name" : "MOUMININA HASAN MIM",
      "xp_points" : 1135
    },
    {
      "group" : "HUMANITIES",
      "id" : "1147432026HUMD1202425020593",
      "last_updated" : "2025-12-18 08:41:45",
      "level" : "🎯 Explorer",
      "name" : "SUMAIYA KHAN ",
      "xp_points" : 1099
    },
    {
      "group" : "SCIENCE",
      "id" : "1090302026SCIM75",
      "last_updated" : "2026-01-29 15:57:31",
      "level" : "🎯 Explorer",
      "name" : "JANNATUL FERDOUS",
      "xp_points" : 1057
    },
    {
      "group" : "HUMANITIES",
      "id" : "1146792026HUMD0443832",
      "last_updated" : "2025-12-20 00:08:19",
      "level" : "🎯 Explorer",
      "name" : "PRITY RANI SARKAR ",
      "xp_points" : 1045
    },
    {
      "group" : "HUMANITIES",
      "id" : "1090302027HUMD1",
      "last_updated" : "2025-12-21 10:32:52",
      "level" : "🎯 Explorer",
      "name" : "KAZI JANNATUN NUR ",
      "xp_points" : 1005
    },
    {
      "group" : "SCIENCE",
      "id" : "2235562027SCID299",
      "last_updated" : "2025-11-06 17:35:32",
      "level" : "📘 Learner",
      "name" : "SHAKIL MRIDHA ",
      "xp_points" : 971
    },
    {
      "group" : "HUMANITIES",
      "id" : "1090302026HUMD318",
      "last_updated" : "2026-01-22 15:42:11",
      "level" : "📘 Learner",
      "name" : "RASHIDA AKTER",
      "xp_points" : 945
    },
    {
      "group" : "OTHERS",
      "id" : "1146782026691",
      "last_updated" : "2026-02-01 17:57:17",
      "level" : "📘 Learner",
      "name" : "SANJIDA AKTER",
      "xp_points" : 935
    },
    {
      "group" : "SCIENCE",
      "id" : "1090302026SCID250",
      "last_updated" : "2026-01-17 22:58:54",
      "level" : "📘 Learner",
      "name" : "FAHMIDA AKTER ANNI",
      "xp_points" : 925
    },
    {
      "group" : "HUMANITIES",
      "id" : "1090302026HUMD346",
      "last_updated" : "2025-10-30 15:41:05",
      "level" : "📘 Learner",
      "name" : "MST.SOMIYA",
      "xp_points" : 810
    },
    {
      "group" : "HUMANITIES",
      "id" : "1146792026HUMD113",
      "last_updated" : "2025-12-17 23:15:40",
      "level" : "📘 Learner",
      "name" : "DIYA DAS",
      "xp_points" : 810
    },
    {
      "group" : "OTHERS",
      "id" : "11467820261003",
      "last_updated" : "2026-02-04 08:45:03",
      "level" : "📘 Learner",
      "name" : "NADIA AKTER",
      "xp_points" : 775
    },
    {
      "group" : "HUMANITIES",
      "id" : "1146782026HUMD1111",
      "last_updated" : "2025-10-28 08:21:26",
      "level" : "📘 Learner",
      "name" : "SADIA AKTER",
      "xp_points" : 772
    },
    {
      "group" : "BUSINESS",
      "id" : "1090302025BUSD61",
      "last_updated" : "2025-11-03 17:46:32",
      "level" : "📘 Learner",
      "name" : "MST.MONIKA AKTER",
      "xp_points" : 705
    },
    {
      "group" : "SCIENCE",
      "id" : "1090302026SCID338",
      "last_updated" : "2025-10-27 18:30:51",
      "level" : "📘 Learner",
      "name" : "SARMIN AKTAR MONA",
      "xp_points" : 692
    },
    {
      "group" : "SCIENCE",
      "id" : "1090302026SCID117",
      "last_updated" : "2025-10-29 12:13:50",
      "level" : "📘 Learner",
      "name" : "SADIA MEHNAJ",
      "xp_points" : 654
    },
    {
      "group" : "SCIENCE",
      "id" : "1090302027SCID03",
      "last_updated" : "2026-01-08 00:33:07",
      "level" : "📘 Learner",
      "name" : "MAHFUZA SULTANA",
      "xp_points" : 625
    },
    {
      "group" : "BUSINESS",
      "id" : "1090302027BUSD355",
      "last_updated" : "2025-12-14 23:23:15",
      "level" : "📘 Learner",
      "name" : "FARHANA AKTER MIM",
      "xp_points" : 599
    },
    {
      "group" : "BUSINESS",
      "id" : "1090302027BUSD24",
      "last_updated" : "2025-11-03 18:07:49",
      "level" : "📘 Learner",
      "name" : "TANZILA JANNAT SUCHI",
      "xp_points" : 578
    },
    {
      "group" : "HUMANITIES",
      "id" : "1090302027HUMD125",
      "last_updated" : "2025-11-04 08:11:25",
      "level" : "📘 Learner",
      "name" : "ZAKIA HOSSAIN MIM",
      "xp_points" : 572
    },
    {
      "group" : "SCIENCE",
      "id" : "1090302026SCID74",
      "last_updated" : "2026-01-26 14:15:25",
      "level" : "📘 Learner",
      "name" : "TOYA TABASSUM ",
      "xp_points" : 565
    },
    {
      "group" : "SCIENCE",
      "id" : "1090302026SCID115",
      "last_updated" : "2025-12-28 14:27:19",
      "level" : "📘 Learner",
      "name" : "TAHSIN BINTE AMIN",
      "xp_points" : 562
    },
    {
      "group" : "HUMANITIES",
      "id" : "1090302027HUMDHUMM374",
      "last_updated" : "2025-11-24 09:42:14",
      "level" : "📘 Learner",
      "name" : "ISRAT JAHAN MONIRA",
      "xp_points" : 546
    },
    {
      "group" : "BUSINESS",
      "id" : "1090302027BUSD198",
      "last_updated" : "2025-12-24 08:07:22",
      "level" : "🔰 Newcomer",
      "name" : "TANJILA AFRIN RATRI",
      "xp_points" : 478
    },
    {
      "group" : "HUMANITIES",
      "id" : "1146782026HUMD1107",
      "last_updated" : "2026-02-02 07:13:35",
      "level" : "🔰 Newcomer",
      "name" : "SHANTA AKTAR",
      "xp_points" : 476
    },
    {
      "group" : "BUSINESS",
      "id" : "1090302027BUSD380",
      "last_updated" : "2025-11-22 22:24:25",
      "level" : "🔰 Newcomer",
      "name" : "FAHMIDA TUSLIM RATRI",
      "xp_points" : 471
    },
    {
      "group" : "BUSINESS",
      "id" : "1090302027BUSM532534",
      "last_updated" : "2025-11-23 15:15:14",
      "level" : "🔰 Newcomer",
      "name" : "AFRIN JAHAN TITHI",
      "xp_points" : 450
    },
    {
      "group" : "SCIENCE",
      "id" : "1090302027SCIM121380",
      "last_updated" : "2025-11-19 14:16:09",
      "level" : "🔰 Newcomer",
      "name" : "SANIYA AKAND ",
      "xp_points" : 433
    },
    {
      "group" : "HUMANITIES",
      "id" : "1146782026HUMD218",
      "last_updated" : "2025-11-05 13:24:43",
      "level" : "🔰 Newcomer",
      "name" : "BORSHA KHAN",
      "xp_points" : 432
    },
    {
      "group" : "SCIENCE",
      "id" : "1090302027SCID451",
      "last_updated" : "2025-11-03 17:25:24",
      "level" : "🔰 Newcomer",
      "name" : "SHAMOLY AKTER REYA ",
      "xp_points" : 417
    },
    {
      "group" : "BUSINESS",
      "id" : "1090302025BUSM26",
      "last_updated" : "2025-11-17 18:40:32",
      "level" : "🔰 Newcomer",
      "name" : "MARUFA AKTER JUI",
      "xp_points" : 413
    },
    {
      "group" : "SCIENCE",
      "id" : "1090302027SCID144268",
      "last_updated" : "2026-02-03 09:42:31",
      "level" : "🔰 Newcomer",
      "name" : "TRISHNA CHAKRABARTI ",
      "xp_points" : 406
    },
    {
      "group" : "OTHERS",
      "id" : "1090302027305",
      "last_updated" : "2026-01-01 23:43:24",
      "level" : "🔰 Newcomer",
      "name" : "SAMIA AKTER",
      "xp_points" : 390
    },
    {
      "group" : "SCIENCE",
      "id" : "1090302027SCID341",
      "last_updated" : "2025-10-30 19:23:38",
      "level" : "🔰 Newcomer",
      "name" : "FATEMA HOSSAIN",
      "xp_points" : 388
    },
    {
      "group" : "BUSINESS",
      "id" : "1090302027BUSD81",
      "last_updated" : "2025-10-29 19:54:36",
      "level" : "🔰 Newcomer",
      "name" : "JIDNI",
      "xp_points" : 381
    },
    {
      "group" : "SCIENCE",
      "id" : "1090302027SCID68",
      "last_updated" : "2025-10-27 18:41:07",
      "level" : "🔰 Newcomer",
      "name" : "KARIMUN SARKAR LAMIA",
      "xp_points" : 377
    },
    {
      "group" : "SCIENCE",
      "id" : "1090302027SCID43",
      "last_updated" : "2025-11-02 16:36:30",
      "level" : "🔰 Newcomer",
      "name" : "SHAMIMA AKTER MIM",
      "xp_points" : 375
    },
    {
      "id" : "109030202560",
      "last_updated" : "2025-12-20 20:26:49",
      "level" : "🔰 Newcomer",
      "name" : "MOSA.AFRINAKTER",
      "xp_points" : 358
    },
    {
      "group" : "BUSINESS",
      "id" : "1090302027BUSD125",
      "last_updated" : "2025-10-29 21:09:24",
      "level" : "🔰 Newcomer",
      "name" : "SADIA AKTER",
      "xp_points" : 348
    },
    {
      "group" : "BUSINESS",
      "id" : "1090302027BUSD365",
      "last_updated" : "2025-11-13 15:08:39",
      "level" : "🔰 Newcomer",
      "name" : "SOSTY DEVNATH",
      "xp_points" : 339
    },
    {
      "group" : "SCIENCE",
      "id" : "1090302027SCID44",
      "last_updated" : "2025-10-30 16:44:17",
      "level" : "🔰 Newcomer",
      "name" : "SAMIA SULTANA",
      "xp_points" : 333
    },
    {
      "group" : "HUMANITIES",
      "id" : "1146782026HUMD1149",
      "last_updated" : "2026-01-06 13:03:07",
      "level" : "🔰 Newcomer",
      "name" : "PAYEL AKTER",
      "xp_points" : 333
    },
    {
      "group" : "HUMANITIES",
      "id" : "1090302026HUMD50",
      "last_updated" : "2025-11-05 11:35:34",
      "level" : "🔰 Newcomer",
      "name" : "FAHMIDA",
      "xp_points" : 328
    },
    {
      "group" : "BUSINESS",
      "id" : "1090302027BUSM93",
      "last_updated" : "2025-11-08 12:11:36",
      "level" : "🔰 Newcomer",
      "name" : "AFROGA AKTER AKHI",
      "xp_points" : 324
    },
    {
      "group" : "SCIENCE",
      "id" : "1090302027SCID02",
      "last_updated" : "2025-11-05 18:09:37",
      "level" : "🔰 Newcomer",
      "name" : "SARA TABASSUM",
      "xp_points" : 318
    },
    {
      "id" : "109030202660",
      "last_updated" : "2026-01-01 19:57:13",
      "level" : "🔰 Newcomer",
      "name" : "SADIYASULTANAMADOBI",
      "xp_points" : 318
    },
    {
      "group" : "HUMANITIES",
      "id" : "1090302027HUMDHUMM55",
      "last_updated" : "2025-11-16 21:04:05",
      "level" : "🔰 Newcomer",
      "name" : "MARIYA AKTER PRIYA",
      "xp_points" : 317
    },
    {
      "group" : "SCIENCE",
      "id" : "1090302026SCID213",
      "last_updated" : "2026-01-24 21:17:01",
      "level" : "🔰 Newcomer",
      "name" : "JANNATUL BINTE SALAM",
      "xp_points" : 308
    },
    {
      "group" : "SCIENCE",
      "id" : "1090302026SCIM118",
      "last_updated" : "2025-11-02 21:49:30",
      "level" : "🔰 Newcomer",
      "name" : "SONGI SHATHI",
      "xp_points" : 307
    },
    {
      "group" : "BUSINESS",
      "id" : "1090302026BUSD0099",
      "last_updated" : "2025-10-28 18:29:45",
      "level" : "🔰 Newcomer",
      "name" : "SADIRA JAHAN TAKFY",
      "xp_points" : 297
    },
    {
      "group" : "HUMANITIES",
      "id" : "1090302025HUMM346",
      "last_updated" : "2025-12-15 19:14:22",
      "level" : "🔰 Newcomer",
      "name" : "MST SOMIYA",
      "xp_points" : 293
    },
    {
      "group" : "SCIENCE",
      "id" : "1090302027SCID11",
      "last_updated" : "2025-10-28 17:10:14",
      "level" : "🔰 Newcomer",
      "name" : "TAZIDA TAHSIN ADITI",
      "xp_points" : 292
    },
    {
      "group" : "BUSINESS",
      "id" : "1090302027BUSD366",
      "last_updated" : "2026-02-12 20:58:54",
      "level" : "🔰 Newcomer",
      "name" : "TRINA RANI SUTRADHAR",
      "xp_points" : 287
    },
    {
      "group" : "HUMANITIES",
      "id" : "1090302026HUMD305",
      "last_updated" : "2026-02-07 22:39:38",
      "level" : "🔰 Newcomer",
      "name" : "SEJUTI",
      "xp_points" : 277
    },
    {
      "group" : "SCIENCE",
      "id" : "1090302026SCID310",
      "last_updated" : "2026-01-25 19:14:21",
      "level" : "🔰 Newcomer",
      "name" : "RIDWANA ALI",
      "xp_points" : 276
    },
    {
      "group" : "HUMANITIES",
      "id" : "1090302027HUMD305",
      "last_updated" : "2025-10-31 13:08:39",
      "level" : "🔰 Newcomer",
      "name" : "SAMIA AKTER",
      "xp_points" : 258
    },
    {
      "group" : "BUSINESS",
      "id" : "1090302027BUSD49",
      "last_updated" : "2025-11-02 16:43:08",
      "level" : "🔰 Newcomer",
      "name" : "MISHKATE NOOR MAGHLA",
      "xp_points" : 257
    },
    {
      "group" : "BUSINESS",
      "id" : "1090302027BUSD28",
      "last_updated" : "2025-10-29 22:15:25",
      "level" : "🔰 Newcomer",
      "name" : "KHADIJA  AKTER RIPA",
      "xp_points" : 251
    },
    {
      "group" : "BUSINESS",
      "id" : "1090302026BUSD252",
      "last_updated" : "2026-01-13 11:55:29",
      "level" : "🔰 Newcomer",
      "name" : "SADIA AKTER",
      "xp_points" : 249
    },
    {
      "group" : "BUSINESS",
      "id" : "1090302026BUSD76",
      "last_updated" : "2025-10-29 00:07:35",
      "level" : "🔰 Newcomer",
      "name" : "SUMAIYA AKTER",
      "xp_points" : 245
    },
    {
      "group" : "BUSINESS",
      "id" : "1090302026BUSD427",
      "last_updated" : "2025-10-28 20:20:09",
      "level" : "🔰 Newcomer",
      "name" : "MOHONA MOLLA",
      "xp_points" : 242
    },
    {
      "group" : "SCIENCE",
      "id" : "1090302026SCID272",
      "last_updated" : "2026-01-12 02:18:15",
      "level" : "🔰 Newcomer",
      "name" : "SADIA",
      "xp_points" : 238
    },
    {
      "group" : "BUSINESS",
      "id" : "1090302026BUSD201",
      "last_updated" : "2026-01-17 16:21:16",
      "level" : "🔰 Newcomer",
      "name" : "CHAITY",
      "xp_points" : 238
    },
    {
      "group" : "HUMANITIES",
      "id" : "1146782027HUMD210",
      "last_updated" : "2026-02-07 10:03:22",
      "level" : "🔰 Newcomer",
      "name" : "MST SUMAIYA AKTER JUI",
      "xp_points" : 238
    },
    {
      "group" : "SCIENCE",
      "id" : "1090302026SCID23",
      "last_updated" : "2025-11-09 20:33:47",
      "level" : "🔰 Newcomer",
      "name" : "NAWSHEEN KHAN NIPUN",
      "xp_points" : 236
    },
    {
      "group" : "SCIENCE",
      "id" : "1090302026SCID367",
      "last_updated" : "2025-11-10 00:37:24",
      "level" : "🔰 Newcomer",
      "name" : "AYSHA TABASSOM TANHA",
      "xp_points" : 235
    },
    {
      "group" : "HUMANITIES",
      "id" : "1090302026HUMD418",
      "last_updated" : "2025-10-27 21:10:24",
      "level" : "🔰 Newcomer",
      "name" : "AFIAJAHANAFRIN",
      "xp_points" : 235
    },
    {
      "group" : "SCIENCE",
      "id" : "1090302026SCID233",
      "last_updated" : "2025-10-30 18:49:44",
      "level" : "🔰 Newcomer",
      "name" : "TASMIA RIM ",
      "xp_points" : 233
    },
    {
      "group" : "SCIENCE",
      "id" : "1090302026SCIM108",
      "last_updated" : "2025-11-09 18:00:52",
      "level" : "🔰 Newcomer",
      "name" : "FARIHA CHOUDHURY",
      "xp_points" : 231
    },
    {
      "group" : "HUMANITIES",
      "id" : "1090302026HUMD26",
      "last_updated" : "2025-11-07 21:51:27",
      "level" : "🔰 Newcomer",
      "name" : "MONIRA SULTANA MUKTA",
      "xp_points" : 230
    },
    {
      "group" : "HUMANITIES",
      "id" : "1090302026HUMD354",
      "last_updated" : "2026-01-17 23:04:25",
      "level" : "🔰 Newcomer",
      "name" : "JANNATUL FERDOUS JUTHI",
      "xp_points" : 230
    },
    {
      "group" : "BUSINESS",
      "id" : "1090302025BUSD60",
      "last_updated" : "2025-11-04 15:48:42",
      "level" : "🔰 Newcomer",
      "name" : "MOSA.AFRINAKTER",
      "xp_points" : 229
    },
    {
      "group" : "HUMANITIES",
      "id" : "1090302026HUMD385",
      "last_updated" : "2026-01-16 21:47:05",
      "level" : "🔰 Newcomer",
      "name" : "NILA AKTER",
      "xp_points" : 229
    },
    {
      "group" : "BUSINESS",
      "id" : "1090302026BUSD94",
      "last_updated" : "2025-11-06 21:00:30",
      "level" : "🔰 Newcomer",
      "name" : "ESRAT JAHAN TABIYA",
      "xp_points" : 228
    },
    {
      "group" : "BUSINESS",
      "id" : "1090302027BUSD307",
      "last_updated" : "2025-11-24 11:17:17",
      "level" : "🔰 Newcomer",
      "name" : "MST.ZAKIA SULTANA",
      "xp_points" : 227
    },
    {
      "group" : "HUMANITIES",
      "id" : "1090302026HUMD104",
      "last_updated" : "2025-11-08 12:09:16",
      "level" : "🔰 Newcomer",
      "name" : "TAMANNA ISLAM",
      "xp_points" : 224
    },
    {
      "id" : "109030202561",
      "last_updated" : "2025-12-21 09:57:43",
      "level" : "🔰 Newcomer",
      "name" : "MST.MONIKA AKTER",
      "xp_points" : 223
    },
    {
      "group" : "BUSINESS",
      "id" : "1090302026BUSD158",
      "last_updated" : "2025-11-09 10:32:33",
      "level" : "🔰 Newcomer",
      "name" : "TAHMINA AKTER TAMANNA",
      "xp_points" : 218
    },
    {
      "group" : "BUSINESS",
      "id" : "1090302026BUSM401",
      "last_updated" : "2025-12-30 13:09:47",
      "level" : "🔰 Newcomer",
      "name" : "BVA MONI",
      "xp_points" : 206
    },
    {
      "group" : "OTHERS",
      "id" : "1090302026325",
      "last_updated" : "2025-12-28 13:36:37",
      "level" : "🔰 Newcomer",
      "name" : "ALEMATUSSADIA",
      "xp_points" : 204
    },
    {
      "group" : "HUMANITIES",
      "id" : "1090302027HUMM287",
      "last_updated" : "2025-12-21 13:26:27",
      "level" : "🔰 Newcomer",
      "name" : "SAMIYA AZHAR ",
      "xp_points" : 198
    },
    {
      "group" : "SCIENCE",
      "id" : "1090302027SCID259",
      "last_updated" : "2025-11-10 14:52:01",
      "level" : "🔰 Newcomer",
      "name" : "MAZRIHA SULTANA MEDHA ",
      "xp_points" : 192
    },
    {
      "group" : "HUMANITIES",
      "id" : "1090302026HUMD100",
      "last_updated" : "2026-01-07 08:29:40",
      "level" : "🔰 Newcomer",
      "name" : "NOOR",
      "xp_points" : 192
    },
    {
      "group" : "OTHERS",
      "id" : "1090302027398",
      "last_updated" : "2025-12-18 23:01:14",
      "level" : "🔰 Newcomer",
      "name" : "SHIPA",
      "xp_points" : 189
    },
    {
      "group" : "SCIENCE",
      "id" : "1090302026SCID255",
      "last_updated" : "2025-11-08 12:01:53",
      "level" : "🔰 Newcomer",
      "name" : "LUBABA ISLAM",
      "xp_points" : 186
    },
    {
      "group" : "BUSINESS",
      "id" : "1090302026BUSD24",
      "last_updated" : "2025-11-10 00:13:42",
      "level" : "🔰 Newcomer",
      "name" : "KOTHA SAHA",
      "xp_points" : 184
    },
    {
      "group" : "HUMANITIES",
      "id" : "1090302026HUMD239",
      "last_updated" : "2025-11-07 06:16:54",
      "level" : "🔰 Newcomer",
      "name" : "HUMAIRA JANNAT",
      "xp_points" : 176
    },
    {
      "group" : "SCIENCE",
      "id" : "1090302027SCIM14",
      "last_updated" : "2026-01-02 18:53:53",
      "level" : "🔰 Newcomer",
      "name" : "TAYIBA TAHSIN RIZMI",
      "xp_points" : 173
    },
    {
      "group" : "SCIENCE",
      "id" : "1090302025SCID239905",
      "last_updated" : "2025-11-24 18:28:18",
      "level" : "🔰 Newcomer",
      "name" : "NAFIZA ISLAM",
      "xp_points" : 171
    },
    {
      "group" : "HUMANITIES",
      "id" : "1090302027HUMD227",
      "last_updated" : "2025-11-24 20:28:21",
      "level" : "🔰 Newcomer",
      "name" : "MOST INUN NAHAR TAIYABA SANI",
      "xp_points" : 171
    },
    {
      "group" : "SCIENCE",
      "id" : "1090302026SCID373",
      "last_updated" : "2026-01-16 20:18:18",
      "level" : "🔰 Newcomer",
      "name" : "TAMANNA TASNIM DIPU ",
      "xp_points" : 171
    },
    {
      "group" : "BUSINESS",
      "id" : "1090302027BUSM48",
      "last_updated" : "2025-11-12 22:59:17",
      "level" : "🔰 Newcomer",
      "name" : "TAJMUN FIDDA",
      "xp_points" : 168
    },
    {
      "group" : "BUSINESS",
      "id" : "1090302026BUSD258",
      "last_updated" : "2025-11-08 22:04:39",
      "level" : "🔰 Newcomer",
      "name" : "RIFATUNNESA HUMAIRA",
      "xp_points" : 166
    },
    {
      "group" : "HUMANITIES",
      "id" : "1090302027HUMDHUMM114",
      "last_updated" : "2025-11-04 20:29:10",
      "level" : "🔰 Newcomer",
      "name" : "MALIHA AKTER FAHIMA ",
      "xp_points" : 165
    },
    {
      "group" : "SCIENCE",
      "id" : "1090302026SCIM111",
      "last_updated" : "2025-12-01 04:39:12",
      "level" : "🔰 Newcomer",
      "name" : "TAYYEBAH",
      "xp_points" : 162
    },
    {
      "group" : "OTHERS",
      "id" : "1090302026118",
      "last_updated" : "2026-01-07 18:28:36",
      "level" : "🔰 Newcomer",
      "name" : "MARJAN SHATHI ",
      "xp_points" : 160
    },
    {
      "group" : "SCIENCE",
      "id" : "1090302027SCID84",
      "last_updated" : "2025-10-28 17:02:07",
      "level" : "🔰 Newcomer",
      "name" : "FATEMA AKTER PRITY ",
      "xp_points" : 157
    },
    {
      "group" : "BUSINESS",
      "id" : "1090302027BUSD150",
      "last_updated" : "2025-10-28 19:43:30",
      "level" : "🔰 Newcomer",
      "name" : "SHABIHA AFTER EMA",
      "xp_points" : 155
    },
    {
      "group" : "SCIENCE",
      "id" : "1090302027SCID289",
      "last_updated" : "2025-11-05 22:13:52",
      "level" : "🔰 Newcomer",
      "name" : "NUSRAT JAHAN",
      "xp_points" : 154
    },
    {
      "group" : "SCIENCE",
      "id" : "1090302026SCIM206",
      "last_updated" : "2025-11-09 08:42:33",
      "level" : "🔰 Newcomer",
      "name" : "SANJIDA KHANOM SUMI",
      "xp_points" : 150
    },
    {
      "group" : "SCIENCE",
      "id" : "1090302026SCID180",
      "last_updated" : "2025-11-12 12:59:39",
      "level" : "🔰 Newcomer",
      "name" : "MAHANAJ PATWARY",
      "xp_points" : 147
    },
    {
      "group" : "BUSINESS",
      "id" : "1090302025BUSD187",
      "last_updated" : "2025-12-13 16:47:23",
      "level" : "🔰 Newcomer",
      "name" : "AMENA AKTER ",
      "xp_points" : 144
    },
    {
      "group" : "SCIENCE",
      "id" : "1090302026SCID281",
      "last_updated" : "2025-11-02 16:37:25",
      "level" : "🔰 Newcomer",
      "name" : "SYEDA HUMAIRA BARI",
      "xp_points" : 142
    },
    {
      "group" : "BUSINESS",
      "id" : "1090302026BUSM246",
      "last_updated" : "2025-11-07 19:36:51",
      "level" : "🔰 Newcomer",
      "name" : "MASUMA AREFIN DIPA",
      "xp_points" : 139
    },
    {
      "group" : "SCIENCE",
      "id" : "1090302026SCID369",
      "last_updated" : "2025-11-09 21:51:19",
      "level" : "🔰 Newcomer",
      "name" : "SAYMA YEASMIN TITHY ",
      "xp_points" : 139
    },
    {
      "group" : "HUMANITIES",
      "id" : "1090302026HUMD231",
      "last_updated" : "2025-11-06 19:40:15",
      "level" : "🔰 Newcomer",
      "name" : "TANJILA AKTER",
      "xp_points" : 135
    },
    {
      "group" : "SCIENCE",
      "id" : "1090302027SCIM122909",
      "last_updated" : "2025-11-26 00:05:22",
      "level" : "🔰 Newcomer",
      "name" : "AYESA AKTER",
      "xp_points" : 135
    },
    {
      "group" : "HUMANITIES",
      "id" : "1090302027HUMD398",
      "last_updated" : "2025-11-13 21:30:56",
      "level" : "🔰 Newcomer",
      "name" : "SHIPA",
      "xp_points" : 129
    },
    {
      "group" : "SCIENCE",
      "id" : "1090302026SCID353",
      "last_updated" : "2025-11-09 22:43:21",
      "level" : "🔰 Newcomer",
      "name" : "FAHMIDA TAHASIN",
      "xp_points" : 124
    },
    {
      "group" : "SCIENCE",
      "id" : "1090302027SCID313",
      "last_updated" : "2025-11-23 00:18:04",
      "level" : "🔰 Newcomer",
      "name" : "SANJIDA AKTHER MIM ",
      "xp_points" : 123
    },
    {
      "group" : "BUSINESS",
      "id" : "1090302027BUSD149",
      "last_updated" : "2025-11-09 12:39:47",
      "level" : "🔰 Newcomer",
      "name" : "JAHIN MAISHA",
      "xp_points" : 120
    },
    {
      "group" : "BUSINESS",
      "id" : "1090302027BUSD21",
      "last_updated" : "2025-11-05 18:53:52",
      "level" : "🔰 Newcomer",
      "name" : "MEHABIN AKTER MISU",
      "xp_points" : 116
    },
    {
      "group" : "BUSINESS",
      "id" : "1090302026BUSD187",
      "last_updated" : "2025-11-09 08:02:33",
      "level" : "🔰 Newcomer",
      "name" : "NUSRAT JAHAN NUPOR",
      "xp_points" : 116
    },
    {
      "group" : "SCIENCE",
      "id" : "1090302027SCIM160",
      "last_updated" : "2025-11-17 12:57:19",
      "level" : "🔰 Newcomer",
      "name" : "ASIA SHOVA",
      "xp_points" : 116
    },
    {
      "group" : "HUMANITIES",
      "id" : "1090942027HUMDHUMM300",
      "last_updated" : "2025-11-24 20:15:07",
      "level" : "🔰 Newcomer",
      "name" : "KHADIZATUL KUBRA PAPIYA",
      "xp_points" : 115
    },
    {
      "group" : "SCIENCE",
      "id" : "1146782026SCID1007",
      "last_updated" : "2025-10-27 15:53:08",
      "level" : "🔰 Newcomer",
      "name" : "NUHSANAT TASNIA",
      "xp_points" : 115
    },
    {
      "group" : "HUMANITIES",
      "id" : "1146782026HUMD691",
      "last_updated" : "2025-12-03 09:31:25",
      "level" : "🔰 Newcomer",
      "name" : "SANJIDA AKTER",
      "xp_points" : 114
    },
    {
      "group" : "HUMANITIES",
      "id" : "1146782026HUMD1132",
      "last_updated" : "2025-12-01 20:05:12",
      "level" : "🔰 Newcomer",
      "name" : "ANONYA AKTHER",
      "xp_points" : 114
    },
    {
      "group" : "HUMANITIES",
      "id" : "1146782026HUMDHUMM1132",
      "last_updated" : "2025-11-24 10:26:35",
      "level" : "🔰 Newcomer",
      "name" : "ANONYA AKTHER",
      "xp_points" : 113
    },
    {
      "group" : "BUSINESS",
      "id" : "1090302027BUSM407",
      "last_updated" : "2026-01-16 14:09:08",
      "level" : "🔰 Newcomer",
      "name" : "SHARMIN KHATUN ",
      "xp_points" : 113
    },
    {
      "group" : "HUMANITIES",
      "id" : "1090302027HUMD4001",
      "last_updated" : "2025-11-23 22:18:22",
      "level" : "🔰 Newcomer",
      "name" : "NUSRAT JAHAN KHUSBU ",
      "xp_points" : 112
    },
    {
      "group" : "HUMANITIES",
      "id" : "1090302027HUMD244",
      "last_updated" : "2026-02-02 15:12:32",
      "level" : "🔰 Newcomer",
      "name" : "HALIMA",
      "xp_points" : 112
    },
    {
      "group" : "SCIENCE",
      "id" : "1090302026SCID202",
      "last_updated" : "2025-11-06 18:39:51",
      "level" : "🔰 Newcomer",
      "name" : "MIMTAUN JANNAT",
      "xp_points" : 111
    },
    {
      "group" : "OTHERS",
      "id" : "11467820261111",
      "last_updated" : "2026-02-01 00:04:25",
      "level" : "🔰 Newcomer",
      "name" : "SADIA AKTER",
      "xp_points" : 108
    },
    {
      "group" : "SCIENCE",
      "id" : "1090302026SCID28",
      "last_updated" : "2025-11-06 19:50:22",
      "level" : "🔰 Newcomer",
      "name" : "MST FATEMA JANNAT",
      "xp_points" : 106
    },
    {
      "group" : "BUSINESS",
      "id" : "1090302026BUSD286",
      "last_updated" : "2026-01-26 06:48:38",
      "level" : "🔰 Newcomer",
      "name" : "NURJAHAN",
      "xp_points" : 106
    },
    {
      "group" : "HUMANITIES",
      "id" : "1146782026HUMDHUMM1101",
      "last_updated" : "2025-11-03 01:43:24",
      "level" : "🔰 Newcomer",
      "name" : "TASNIM AKTER SOWA",
      "xp_points" : 105
    },
    {
      "group" : "SCIENCE",
      "id" : "1090302026SCID229",
      "last_updated" : "2025-11-08 23:41:13",
      "level" : "🔰 Newcomer",
      "name" : "KARIMA AKTET",
      "xp_points" : 104
    },
    {
      "group" : "HUMANITIES",
      "id" : "1090302026HUMDHUMM284",
      "last_updated" : "2025-11-09 23:31:46",
      "level" : "🔰 Newcomer",
      "name" : "KHADIZA AKHTER OTHOI ",
      "xp_points" : 104
    },
    {
      "group" : "SCIENCE",
      "id" : "1090302027SCIM78",
      "last_updated" : "2025-11-24 09:40:43",
      "level" : "🔰 Newcomer",
      "name" : "SAMIA ISLAM ",
      "xp_points" : 104
    },
    {
      "group" : "SCIENCE",
      "id" : "1090302026SCID362",
      "last_updated" : "2025-11-10 10:49:33",
      "level" : "🔰 Newcomer",
      "name" : "MAHIMA SANJANA MAHI",
      "xp_points" : 103
    },
    {
      "group" : "BUSINESS",
      "id" : "1090302026BUSD75",
      "last_updated" : "2025-11-08 10:28:05",
      "level" : "🔰 Newcomer",
      "name" : "JANNAT TARA RAKHI",
      "xp_points" : 101
    },
    {
      "group" : "SCIENCE",
      "id" : "1090302026SCIM115",
      "last_updated" : "2025-11-04 22:01:06",
      "level" : "🔰 Newcomer",
      "name" : "TAHSIN BINTE",
      "xp_points" : 100
    },
    {
      "group" : "HUMANITIES",
      "id" : "1090302027HUMD100",
      "last_updated" : "2025-11-23 21:41:34",
      "level" : "🔰 Newcomer",
      "name" : "MITU AKTER LIZA",
      "xp_points" : 99
    },
    {
      "group" : "SCIENCE",
      "id" : "1090302025SCID121363",
      "last_updated" : "2025-10-27 18:24:08",
      "level" : "🔰 Newcomer",
      "name" : "SHAIRA ISLAM ",
      "xp_points" : 99
    },
    {
      "group" : "BUSINESS",
      "id" : "1090302027BUSM235",
      "last_updated" : "2025-11-24 20:07:08",
      "level" : "🔰 Newcomer",
      "name" : "MIFTAHOUL JANNAT SELME ",
      "xp_points" : 98
    },
    {
      "group" : "HUMANITIES",
      "id" : "1147432027HUMD641",
      "last_updated" : "2025-12-11 23:24:04",
      "level" : "🔰 Newcomer",
      "name" : "SOHA",
      "xp_points" : 98
    },
    {
      "group" : "SCIENCE",
      "id" : "1090302027SCIM228563",
      "last_updated" : "2025-11-23 20:38:35",
      "level" : "🔰 Newcomer",
      "name" : "ELMA JAMAN",
      "xp_points" : 97
    },
    {
      "group" : "BUSINESS",
      "id" : "1090302026BUSD259",
      "last_updated" : "2025-11-09 19:42:40",
      "level" : "🔰 Newcomer",
      "name" : "TAHMINA AKTER",
      "xp_points" : 96
    },
    {
      "group" : "BUSINESS",
      "id" : "1090302025BUSM436",
      "last_updated" : "2025-12-31 09:52:16",
      "level" : "🔰 Newcomer",
      "name" : "MST JAKIA SULTANA",
      "xp_points" : 96
    },
    {
      "group" : "SCIENCE",
      "id" : "1090302026SCIM87",
      "last_updated" : "2025-11-08 22:40:47",
      "level" : "🔰 Newcomer",
      "name" : "EVA AKTER MIM",
      "xp_points" : 92
    },
    {
      "group" : "BUSINESS",
      "id" : "1090302026BUSD406",
      "last_updated" : "2025-11-09 20:44:19",
      "level" : "🔰 Newcomer",
      "name" : "SHANTA AKTER RUBI",
      "xp_points" : 92
    },
    {
      "group" : "SCIENCE",
      "id" : "1090302026SCIM184",
      "last_updated" : "2025-11-10 11:19:22",
      "level" : "🔰 Newcomer",
      "name" : "MARYAM SIKDER LAIMA",
      "xp_points" : 92
    },
    {
      "group" : "OTHERS",
      "id" : "1090302026233",
      "last_updated" : "2026-01-18 11:27:04",
      "level" : "🔰 Newcomer",
      "name" : "TASMIA RIM ",
      "xp_points" : 92
    },
    {
      "group" : "SCIENCE",
      "id" : "1090302026SCID297",
      "last_updated" : "2025-11-28 18:55:16",
      "level" : "🔰 Newcomer",
      "name" : "ELMA ISLAM SIMI",
      "xp_points" : 91
    },
    {
      "group" : "SCIENCE",
      "id" : "1090302026SCID176",
      "last_updated" : "2025-11-09 13:06:36",
      "level" : "🔰 Newcomer",
      "name" : "TITHI ROY",
      "xp_points" : 87
    },
    {
      "group" : "HUMANITIES",
      "id" : "1147422026HUMD2127",
      "last_updated" : "2025-12-17 21:51:07",
      "level" : "🔰 Newcomer",
      "name" : "FALGUNI CHAKROBORTY ARTHY",
      "xp_points" : 86
    },
    {
      "group" : "BUSINESS",
      "id" : "1090302026BUSM19",
      "last_updated" : "2025-11-08 21:57:19",
      "level" : "🔰 Newcomer",
      "name" : "SHRABONTI CHANDA",
      "xp_points" : 85
    },
    {
      "group" : "HUMANITIES",
      "id" : "1090302027HUMDHUMM17",
      "last_updated" : "2025-11-24 19:20:02",
      "level" : "🔰 Newcomer",
      "name" : "FATIMA ISLAM.",
      "xp_points" : 85
    },
    {
      "group" : "SCIENCE",
      "id" : "1090302026SCID270",
      "last_updated" : "2025-11-09 09:12:37",
      "level" : "🔰 Newcomer",
      "name" : "MST. SANJANA ISLAM",
      "xp_points" : 84
    },
    {
      "group" : "HUMANITIES",
      "id" : "1090302027HUMD112",
      "last_updated" : "2025-11-01 12:53:32",
      "level" : "🔰 Newcomer",
      "name" : "AFSANA PARVIN SUMA",
      "xp_points" : 83
    },
    {
      "group" : "BUSINESS",
      "id" : "1090302026BUSM257",
      "last_updated" : "2025-11-08 21:11:27",
      "level" : "🔰 Newcomer",
      "name" : "HALIMA TUZ SADIA",
      "xp_points" : 82
    },
    {
      "group" : "HUMANITIES",
      "id" : "1146782027HUMD206",
      "last_updated" : "2026-02-14 01:12:37",
      "level" : "🔰 Newcomer",
      "name" : "NABILA ",
      "xp_points" : 81
    },
    {
      "group" : "HUMANITIES",
      "id" : "1090302026HUMD380",
      "last_updated" : "2025-11-06 21:27:34",
      "level" : "🔰 Newcomer",
      "name" : "ARBI MONY",
      "xp_points" : 80
    },
    {
      "group" : "SCIENCE",
      "id" : "1090302026SCIM230",
      "last_updated" : "2025-11-08 21:05:48",
      "level" : "🔰 Newcomer",
      "name" : "BITUN NAHAR JERIN",
      "xp_points" : 79
    },
    {
      "group" : "SCIENCE",
      "id" : "1090302025SCID121182",
      "last_updated" : "2025-11-25 00:43:15",
      "level" : "🔰 Newcomer",
      "name" : "IFRAT HOSSEN TANHA",
      "xp_points" : 78
    },
    {
      "group" : "BUSINESS",
      "id" : "1090302026BUSD262",
      "last_updated" : "2025-11-26 18:17:57",
      "level" : "🔰 Newcomer",
      "name" : "JANNATUL FERDOUS AKHI",
      "xp_points" : 78
    },
    {
      "group" : "BUSINESS",
      "id" : "1090302026BUSM14",
      "last_updated" : "2026-01-12 15:35:33",
      "level" : "🔰 Newcomer",
      "name" : "RABEYA AKTER RIYA",
      "xp_points" : 77
    },
    {
      "group" : "SCIENCE",
      "id" : "1090302026SCID124",
      "last_updated" : "2025-11-09 00:46:15",
      "level" : "🔰 Newcomer",
      "name" : "AFSANA ISLAM ANIKA",
      "xp_points" : 75
    },
    {
      "group" : "HUMANITIES",
      "id" : "1090302026HUMDHUMM18",
      "last_updated" : "2025-11-08 00:28:06",
      "level" : "🔰 Newcomer",
      "name" : "AFRIN JUNAT REYA",
      "xp_points" : 73
    },
    {
      "group" : "SCIENCE",
      "id" : "1090302027SCID64",
      "last_updated" : "2025-11-19 08:58:58",
      "level" : "🔰 Newcomer",
      "name" : "MST RANI ",
      "xp_points" : 72
    },
    {
      "group" : "OTHERS",
      "id" : "1090302026338",
      "last_updated" : "2026-01-26 00:45:58",
      "level" : "🔰 Newcomer",
      "name" : "SARMIN AKTAR MONA",
      "xp_points" : 72
    },
    {
      "group" : "HUMANITIES",
      "id" : "1090302027HUMDHUMM287",
      "last_updated" : "2025-11-22 01:27:09",
      "level" : "🔰 Newcomer",
      "name" : "SAMIYA AZHAR ",
      "xp_points" : 71
    },
    {
      "group" : "BUSINESS",
      "id" : "1090302026BUSD146",
      "last_updated" : "2026-01-25 22:41:17",
      "level" : "🔰 Newcomer",
      "name" : "BILKIS ISLAM TOYA",
      "xp_points" : 71
    },
    {
      "group" : "SCIENCE",
      "id" : "1146782026SCID1003",
      "last_updated" : "2025-11-13 10:50:12",
      "level" : "🔰 Newcomer",
      "name" : "NADIA AKTER",
      "xp_points" : 70
    },
    {
      "group" : "BUSINESS",
      "id" : "1090302026BUSD368",
      "last_updated" : "2025-11-02 19:19:19",
      "level" : "🔰 Newcomer",
      "name" : "MST.SUMAIYA AKTER",
      "xp_points" : 69
    },
    {
      "group" : "HUMANITIES",
      "id" : "1090302026HUMD325",
      "last_updated" : "2025-11-08 10:34:35",
      "level" : "🔰 Newcomer",
      "name" : "ALEMATUSSADIA",
      "xp_points" : 69
    },
    {
      "group" : "SCIENCE",
      "id" : "1090302026SCIM102",
      "last_updated" : "2025-11-10 07:10:28",
      "level" : "🔰 Newcomer",
      "name" : "NOURIN NUHAS",
      "xp_points" : 69
    },
    {
      "group" : "SCIENCE",
      "id" : "1090302026SCIM88",
      "last_updated" : "2025-11-10 11:02:15",
      "level" : "🔰 Newcomer",
      "name" : "HUHU",
      "xp_points" : 68
    },
    {
      "group" : "SCIENCE",
      "id" : "1090302026SCID63",
      "last_updated" : "2026-01-08 15:08:18",
      "level" : "🔰 Newcomer",
      "name" : "AYESHA AKTER",
      "xp_points" : 68
    },
    {
      "group" : "BUSINESS",
      "id" : "1090302027BUSD34",
      "last_updated" : "2025-10-29 18:08:15",
      "level" : "🔰 Newcomer",
      "name" : "NOOR",
      "xp_points" : 67
    },
    {
      "group" : "HUMANITIES",
      "id" : "1090302027HUMD312",
      "last_updated" : "2025-12-01 18:51:32",
      "level" : "🔰 Newcomer",
      "name" : "ALINA AKTER MEEM",
      "xp_points" : 67
    },
    {
      "group" : "BUSINESS",
      "id" : "1090302026BUSM337",
      "last_updated" : "2026-01-11 18:59:01",
      "level" : "🔰 Newcomer",
      "name" : "ARNIKA AHMED BRISTY",
      "xp_points" : 66
    },
    {
      "group" : "SCIENCE",
      "id" : "1090302027SCID124275",
      "last_updated" : "2025-11-03 22:31:14",
      "level" : "🔰 Newcomer",
      "name" : "ELMA",
      "xp_points" : 65
    },
    {
      "group" : "SCIENCE",
      "id" : "1090302026SCIM94",
      "last_updated" : "2025-11-09 16:18:16",
      "level" : "🔰 Newcomer",
      "name" : "SAMIHA TASNIA OPSHORA",
      "xp_points" : 63
    },
    {
      "group" : "BUSINESS",
      "id" : "1090302026BUSD275",
      "last_updated" : "2025-11-10 18:29:16",
      "level" : "🔰 Newcomer",
      "name" : "SIRAJUM MONIRA ",
      "xp_points" : 63
    },
    {
      "group" : "SCIENCE",
      "id" : "1090302027SCID67",
      "last_updated" : "2025-11-04 07:33:54",
      "level" : "🔰 Newcomer",
      "name" : "SHAMIA TANJIM",
      "xp_points" : 63
    },
    {
      "group" : "HUMANITIES",
      "id" : "1090302027HUMD178",
      "last_updated" : "2026-01-06 22:01:09",
      "level" : "🔰 Newcomer",
      "name" : "TASRIF TAPPA",
      "xp_points" : 63
    },
    {
      "id" : "109030202703",
      "last_updated" : "2025-12-18 18:27:24",
      "level" : "🔰 Newcomer",
      "name" : "MAHFUZA SULTANA",
      "xp_points" : 62
    },
    {
      "group" : "OTHERS",
      "id" : "10903020260099",
      "last_updated" : "2026-01-08 11:26:52",
      "level" : "🔰 Newcomer",
      "name" : "SADIRA JAHAN TAKFY",
      "xp_points" : 62
    },
    {
      "group" : "HUMANITIES",
      "id" : "1090302026HUMD123",
      "last_updated" : "2025-11-02 11:56:29",
      "level" : "🔰 Newcomer",
      "name" : "AZMAINA",
      "xp_points" : 61
    },
    {
      "group" : "OTHERS",
      "id" : "11467820261140",
      "last_updated" : "2025-12-17 11:03:45",
      "level" : "🔰 Newcomer",
      "name" : "ESRAT JAHAN TOMA ",
      "xp_points" : 61
    },
    {
      "group" : "BUSINESS",
      "id" : "1090302026BUSD317",
      "last_updated" : "2025-11-10 08:52:24",
      "level" : "🔰 Newcomer",
      "name" : "FARIA AFRIN",
      "xp_points" : 60
    },
    {
      "group" : "OTHERS",
      "id" : "1090302026346",
      "last_updated" : "2025-12-11 08:15:03",
      "level" : "🔰 Newcomer",
      "name" : "MST.SOMIYA",
      "xp_points" : 60
    },
    {
      "id" : "2027101",
      "last_updated" : "2025-10-22 20:59:09",
      "level" : "🔰 Newcomer",
      "name" : "AFNAN AMIN",
      "xp_points" : 58
    },
    {
      "group" : "SCIENCE",
      "id" : "1090302027SCID286",
      "last_updated" : "2025-11-10 19:07:21",
      "level" : "🔰 Newcomer",
      "name" : "SUMAIYA AKTAR NIJUM ",
      "xp_points" : 57
    },
    {
      "group" : "SCIENCE",
      "id" : "1090302027SCID16",
      "last_updated" : "2025-11-23 20:50:28",
      "level" : "🔰 Newcomer",
      "name" : "SAMEHA JAHAN",
      "xp_points" : 55
    },
    {
      "group" : "OTHERS",
      "id" : "1090302026145",
      "last_updated" : "2025-12-12 16:15:58",
      "level" : "🔰 Newcomer",
      "name" : "TANJINA AKTER ",
      "xp_points" : 55
    },
    {
      "group" : "SCIENCE",
      "id" : "1090302026SCIM301",
      "last_updated" : "2025-11-03 21:03:49",
      "level" : "🔰 Newcomer",
      "name" : "NAOSHIN AFROZ EKRA",
      "xp_points" : 54
    },
    {
      "group" : "HUMANITIES",
      "id" : "1146782026HUMD1133",
      "last_updated" : "2025-10-28 08:21:29",
      "level" : "🔰 Newcomer",
      "name" : "LIZA AKTHER",
      "xp_points" : 53
    },
    {
      "group" : "HUMANITIES",
      "id" : "1090302026HUMD227",
      "last_updated" : "2025-11-06 21:37:39",
      "level" : "🔰 Newcomer",
      "name" : "IFAT JAHAN MIMI",
      "xp_points" : 52
    },
    {
      "group" : "BUSINESS",
      "id" : "1090302026BUSD2655824",
      "last_updated" : "2025-11-09 22:16:44",
      "level" : "🔰 Newcomer",
      "name" : "SHANTA AKTER",
      "xp_points" : 51
    },
    {
      "group" : "HUMANITIES",
      "id" : "1146782027HUMD205",
      "last_updated" : "2026-02-07 10:11:28",
      "level" : "🔰 Newcomer",
      "name" : "SANJIDA SAYMA",
      "xp_points" : 51
    },
    {
      "group" : "BUSINESS",
      "id" : "1090302026BUSM148",
      "last_updated" : "2025-11-08 17:13:56",
      "level" : "🔰 Newcomer",
      "name" : "SAKILA AKTER SALINA",
      "xp_points" : 50
    },
    {
      "group" : "SCIENCE",
      "id" : "1090302026SCIM197",
      "last_updated" : "2025-11-09 06:26:38",
      "level" : "🔰 Newcomer",
      "name" : "SABINA AKTER",
      "xp_points" : 50
    },
    {
      "group" : "HUMANITIES",
      "id" : "1090302026HUMD339",
      "last_updated" : "2025-11-09 21:13:52",
      "level" : "🔰 Newcomer",
      "name" : "TABASSUM TOVA",
      "xp_points" : 50
    },
    {
      "group" : "HUMANITIES",
      "id" : "1090302026HUMDHUMM146",
      "last_updated" : "2025-11-22 08:52:14",
      "level" : "🔰 Newcomer",
      "name" : "TISHA MONI",
      "xp_points" : 50
    },
    {
      "group" : "HUMANITIES",
      "id" : "1146782026HUMD1162",
      "last_updated" : "2026-01-04 23:25:17",
      "level" : "🔰 Newcomer",
      "name" : "SUMAIYA",
      "xp_points" : 50
    },
    {
      "group" : "HUMANITIES",
      "id" : "1090302026HUMM371",
      "last_updated" : "2026-01-08 07:36:09",
      "level" : "🔰 Newcomer",
      "name" : "SADIA AKTER ",
      "xp_points" : 50
    },
    {
      "group" : "BUSINESS",
      "id" : "1090302026BUSD66",
      "last_updated" : "2025-11-08 11:59:32",
      "level" : "🔰 Newcomer",
      "name" : "LIZA AKTER",
      "xp_points" : 48
    },
    {
      "group" : "HUMANITIES",
      "id" : "1090302026HUMD67",
      "last_updated" : "2025-11-09 20:11:29",
      "level" : "🔰 Newcomer",
      "name" : "MST DELOWARE AKTER NYMA",
      "xp_points" : 48
    },
    {
      "group" : "BUSINESS",
      "id" : "1090302026BUSM146",
      "last_updated" : "2025-11-09 23:38:46",
      "level" : "🔰 Newcomer",
      "name" : "BILKISH ISLAM TOYA",
      "xp_points" : 48
    },
    {
      "group" : "BUSINESS",
      "id" : "1090302027BUSD87",
      "last_updated" : "2025-11-23 19:20:40",
      "level" : "🔰 Newcomer",
      "name" : "MUNNI AKTER MONI",
      "xp_points" : 48
    },
    {
      "group" : "HUMANITIES",
      "id" : "1146782026HUMD1170",
      "last_updated" : "2026-01-15 17:50:31",
      "level" : "🔰 Newcomer",
      "name" : "MONIRA SHAH",
      "xp_points" : 48
    },
    {
      "group" : "SCIENCE",
      "id" : "1090302026SCID169",
      "last_updated" : "2025-11-04 21:07:33",
      "level" : "🔰 Newcomer",
      "name" : "TAHIA TASNIM ",
      "xp_points" : 47
    },
    {
      "group" : "HUMANITIES",
      "id" : "1090302026HUMD287",
      "last_updated" : "2025-11-07 14:44:19",
      "level" : "🔰 Newcomer",
      "name" : "SHIMLA AKTER",
      "xp_points" : 46
    },
    {
      "group" : "SCIENCE",
      "id" : "1090302026SCID324",
      "last_updated" : "2025-11-10 08:08:20",
      "level" : "🔰 Newcomer",
      "name" : "SANJIDA AKTER ",
      "xp_points" : 46
    },
    {
      "group" : "BUSINESS",
      "id" : "1090302026BUSD20",
      "last_updated" : "2025-11-08 00:33:27",
      "level" : "🔰 Newcomer",
      "name" : "NUSRAT AFRIN ",
      "xp_points" : 46
    },
    {
      "group" : "BUSINESS",
      "id" : "1090302027BUSM1",
      "last_updated" : "2025-11-23 09:58:17",
      "level" : "🔰 Newcomer",
      "name" : "ABU HASNA ARINA",
      "xp_points" : 46
    },
    {
      "group" : "SCIENCE",
      "id" : "1090302027SCID258",
      "last_updated" : "2025-11-23 10:05:37",
      "level" : "🔰 Newcomer",
      "name" : "FAHIYA AZRIN ",
      "xp_points" : 46
    },
    {
      "group" : "HUMANITIES",
      "id" : "1090302027HUMD70",
      "last_updated" : "2025-11-24 18:45:23",
      "level" : "🔰 Newcomer",
      "name" : "ALPONA AKTER AKHI ",
      "xp_points" : 46
    },
    {
      "group" : "HUMANITIES",
      "id" : "1090302027HUMD49",
      "last_updated" : "2025-12-12 23:15:32",
      "level" : "🔰 Newcomer",
      "name" : "JARIN JAHAN",
      "xp_points" : 46
    },
    {
      "group" : "SCIENCE",
      "id" : "1090302026SCID13",
      "last_updated" : "2025-12-01 07:35:04",
      "level" : "🔰 Newcomer",
      "name" : "SAMIA ALAM",
      "xp_points" : 45
    },
    {
      "id" : "109030202744",
      "last_updated" : "2026-01-08 08:07:41",
      "level" : "🔰 Newcomer",
      "name" : "SAMIA SULTANA",
      "xp_points" : 45
    },
    {
      "group" : "HUMANITIES",
      "id" : "1090302026HUMD36",
      "last_updated" : "2026-02-04 20:49:08",
      "level" : "🔰 Newcomer",
      "name" : "SHAYLA SHARMIN LIYA",
      "xp_points" : 45
    },
    {
      "group" : "SCIENCE",
      "id" : "1090302026SCID285",
      "last_updated" : "2025-11-08 20:39:29",
      "level" : "🔰 Newcomer",
      "name" : "TANJILA RAHMNA TONIMA ",
      "xp_points" : 44
    },
    {
      "group" : "BUSINESS",
      "id" : "1090302026BUSD214",
      "last_updated" : "2025-12-03 20:22:02",
      "level" : "🔰 Newcomer",
      "name" : "LIZA AKTER NOPUR ",
      "xp_points" : 44
    },
    {
      "group" : "SCIENCE",
      "id" : "1090302026SCIM128",
      "last_updated" : "2026-01-25 15:25:16",
      "level" : "🔰 Newcomer",
      "name" : "SAMIHA SALAUDDIN",
      "xp_points" : 44
    },
    {
      "group" : "SCIENCE",
      "id" : "1090302026SCID199",
      "last_updated" : "2025-11-08 12:51:24",
      "level" : "🔰 Newcomer",
      "name" : "SUMAIYA ",
      "xp_points" : 43
    },
    {
      "group" : "SCIENCE",
      "id" : "1090302026SCID87",
      "last_updated" : "2025-11-10 11:36:26",
      "level" : "🔰 Newcomer",
      "name" : " MST MITU KHATUN",
      "xp_points" : 43
    },
    {
      "group" : "BUSINESS",
      "id" : "1090302027BUSD324",
      "last_updated" : "2025-11-25 07:31:51",
      "level" : "🔰 Newcomer",
      "name" : "SADIA",
      "xp_points" : 43
    },
    {
      "group" : "HUMANITIES",
      "id" : "1090302026HUMDHUMM217",
      "last_updated" : "2025-11-09 10:30:35",
      "level" : "🔰 Newcomer",
      "name" : "MST SHOPNA",
      "xp_points" : 41
    },
    {
      "group" : "HUMANITIES",
      "id" : "1090302027HUMD105",
      "last_updated" : "2025-11-24 19:22:12",
      "level" : "🔰 Newcomer",
      "name" : "ASMAUL HOSNA",
      "xp_points" : 40
    },
    {
      "group" : "BUSINESS",
      "id" : "1090302026BUSM183",
      "last_updated" : "2026-01-14 19:08:32",
      "level" : "🔰 Newcomer",
      "name" : "ISRAT JAHAN SHEJOTI",
      "xp_points" : 39
    },
    {
      "group" : "SCIENCE",
      "id" : "1090302027SCID62",
      "last_updated" : "2025-11-24 23:24:15",
      "level" : "🔰 Newcomer",
      "name" : "NUSRAT JAHAN JIM ",
      "xp_points" : 38
    },
    {
      "group" : "HUMANITIES",
      "id" : "1160982025HUMD428407",
      "last_updated" : "2025-11-13 08:48:57",
      "level" : "🔰 Newcomer",
      "name" : "MD HABIBUR RAHMAN SAJEEB ",
      "xp_points" : 37
    },
    {
      "id" : "109030202734",
      "last_updated" : "2025-12-12 19:57:49",
      "level" : "🔰 Newcomer",
      "name" : "NOOR",
      "xp_points" : 37
    },
    {
      "group" : "SCIENCE",
      "id" : "1090302026SCID343",
      "last_updated" : "2025-11-05 12:48:43",
      "level" : "🔰 Newcomer",
      "name" : "SADIA NOWSHIN",
      "xp_points" : 36
    },
    {
      "group" : "BUSINESS",
      "id" : "1090302026BUSM26",
      "last_updated" : "2025-11-06 15:43:06",
      "level" : "🔰 Newcomer",
      "name" : "MARUFA AKTER JUI ",
      "xp_points" : 35
    },
    {
      "group" : "SCIENCE",
      "id" : "1090302026SCID700",
      "last_updated" : "2025-11-09 13:36:13",
      "level" : "🔰 Newcomer",
      "name" : "ITACHI",
      "xp_points" : 35
    },
    {
      "group" : "BUSINESS",
      "id" : "1090302027BUSD357",
      "last_updated" : "2025-11-24 18:38:17",
      "level" : "🔰 Newcomer",
      "name" : "AYSHA SIDDIKE TANHA ",
      "xp_points" : 35
    },
    {
      "group" : "HUMANITIES",
      "id" : "1147432026HUMD379",
      "last_updated" : "2025-12-15 17:21:58",
      "level" : "🔰 Newcomer",
      "name" : "FARIHA ISLAM",
      "xp_points" : 35
    },
    {
      "group" : "SCIENCE",
      "id" : "1090302025SCID187",
      "last_updated" : "2025-11-10 00:13:04",
      "level" : "🔰 Newcomer",
      "name" : "NUREY AFROJ MAHIN",
      "xp_points" : 34
    },
    {
      "group" : "BUSINESS",
      "id" : "1090302027BUSM19",
      "last_updated" : "2025-11-23 19:43:51",
      "level" : "🔰 Newcomer",
      "name" : "NABILA BINTE MOSHAROF ",
      "xp_points" : 34
    },
    {
      "group" : "SCIENCE",
      "id" : "1385792026SCIM40",
      "last_updated" : "2026-01-14 01:22:28",
      "level" : "🔰 Newcomer",
      "name" : "MD.SAKIB AL HASAN IFAD",
      "xp_points" : 33
    },
    {
      "group" : "HUMANITIES",
      "id" : "1090302027HUMD148",
      "last_updated" : "2025-11-15 13:51:52",
      "level" : "🔰 Newcomer",
      "name" : "MARYAM",
      "xp_points" : 32
    },
    {
      "group" : "HUMANITIES",
      "id" : "1234562025HUMD25465",
      "last_updated" : "2025-12-09 01:08:36",
      "level" : "🔰 Newcomer",
      "name" : "JANAN AKTER ",
      "xp_points" : 30
    },
    {
      "group" : "BUSINESS",
      "id" : "1090302027BUSD515628",
      "last_updated" : "2026-02-03 19:35:56",
      "level" : "🔰 Newcomer",
      "name" : "SAMIA AFRIN",
      "xp_points" : 28
    },
    {
      "group" : "BUSINESS",
      "id" : "1090302027BUSD410",
      "last_updated" : "2025-11-24 17:56:51",
      "level" : "🔰 Newcomer",
      "name" : "RIJUANA RITU",
      "xp_points" : 27
    },
    {
      "group" : "OTHERS",
      "id" : "1090302026114",
      "last_updated" : "2025-12-11 13:25:02",
      "level" : "🔰 Newcomer",
      "name" : "MOUMININA HASAN MIM",
      "xp_points" : 26
    },
    {
      "group" : "SCIENCE",
      "id" : "1090302027SCID103",
      "last_updated" : "2025-12-17 06:45:00",
      "level" : "🔰 Newcomer",
      "name" : "SANJUMA ",
      "xp_points" : 26
    },
    {
      "group" : "BUSINESS",
      "id" : "1090302026BUSM427",
      "last_updated" : "2025-11-08 07:02:34",
      "level" : "🔰 Newcomer",
      "name" : "MOHONA MOLLA",
      "xp_points" : 25
    },
    {
      "group" : "BUSINESS",
      "id" : "1090302027BUSM513560",
      "last_updated" : "2025-11-11 17:08:03",
      "level" : "🔰 Newcomer",
      "name" : "MUSLIMA ",
      "xp_points" : 25
    },
    {
      "group" : "BUSINESS",
      "id" : "1090302026BUSD208",
      "last_updated" : "2025-11-12 18:55:47",
      "level" : "🔰 Newcomer",
      "name" : "JANNATI AKTER",
      "xp_points" : 25
    },
    {
      "group" : "HUMANITIES",
      "id" : "1090302027HUMD357",
      "last_updated" : "2025-11-17 22:33:33",
      "level" : "🔰 Newcomer",
      "name" : "MARIYA",
      "xp_points" : 25
    },
    {
      "group" : "SCIENCE",
      "id" : "1090302027SCID135",
      "last_updated" : "2025-11-23 20:18:10",
      "level" : "🔰 Newcomer",
      "name" : "MAHBOBA RAHMAN ",
      "xp_points" : 25
    },
    {
      "group" : "SCIENCE",
      "id" : "1090302027SCID109",
      "last_updated" : "2025-11-25 06:44:32",
      "level" : "🔰 Newcomer",
      "name" : "SAYMA ISLAM TONIHA",
      "xp_points" : 25
    },
    {
      "group" : "SCIENCE",
      "id" : "1090302027SCIM157",
      "last_updated" : "2025-11-25 07:35:44",
      "level" : "🔰 Newcomer",
      "name" : "MASTIKA RAHMAN MOWNATA",
      "xp_points" : 25
    },
    {
      "group" : "OTHERS",
      "id" : "1147432026226",
      "last_updated" : "2025-12-17 10:08:09",
      "level" : "🔰 Newcomer",
      "name" : "MARIA AKTER",
      "xp_points" : 25
    },
    {
      "group" : "BUSINESS",
      "id" : "1090302027BUSD232",
      "last_updated" : "2025-12-23 08:39:28",
      "level" : "🔰 Newcomer",
      "name" : "ESRAT JAHAN ELA",
      "xp_points" : 25
    },
    {
      "group" : "HUMANITIES",
      "id" : "1090302026HUMD89",
      "last_updated" : "2026-01-19 19:01:49",
      "level" : "🔰 Newcomer",
      "name" : "SANJIDA ISLAM NUR",
      "xp_points" : 25
    },
    {
      "group" : "SCIENCE",
      "id" : "1090302027SCID178",
      "last_updated" : "2025-11-04 16:57:37",
      "level" : "🔰 Newcomer",
      "name" : "LILIMA RAHMAN ",
      "xp_points" : 24
    },
    {
      "group" : "HUMANITIES",
      "id" : "1090302026HUMD288",
      "last_updated" : "2025-11-07 06:53:06",
      "level" : "🔰 Newcomer",
      "name" : "JASHMIN KHATUN JUTHI",
      "xp_points" : 24
    },
    {
      "group" : "HUMANITIES",
      "id" : "1090302026HUMD85",
      "last_updated" : "2025-11-09 07:15:23",
      "level" : "🔰 Newcomer",
      "name" : "JEASMIN AKTER JUTHI",
      "xp_points" : 24
    },
    {
      "group" : "BUSINESS",
      "id" : "1090302027BUSD134",
      "last_updated" : "2025-11-09 12:45:35",
      "level" : "🔰 Newcomer",
      "name" : "LAMIYA FERDOUSH MIHA",
      "xp_points" : 24
    },
    {
      "group" : "SCIENCE",
      "id" : "1090302025SCID106",
      "last_updated" : "2025-11-24 20:56:27",
      "level" : "🔰 Newcomer",
      "name" : "MAYESHA MAHJABIN METHILA",
      "xp_points" : 24
    },
    {
      "group" : "SCIENCE",
      "id" : "1090302026SCID111",
      "last_updated" : "2025-12-01 04:41:10",
      "level" : "🔰 Newcomer",
      "name" : "UMME KULSUM TAYYEBAH",
      "xp_points" : 24
    },
    {
      "group" : "SCIENCE",
      "id" : "1090302027SCID121147",
      "last_updated" : "2025-10-30 16:06:41",
      "level" : "🔰 Newcomer",
      "name" : "TANJILA TABASSUM ",
      "xp_points" : 23
    },
    {
      "group" : "BUSINESS",
      "id" : "1090302026BUSD128",
      "last_updated" : "2025-11-07 12:45:52",
      "level" : "🔰 Newcomer",
      "name" : "AFROZA HOSSAIN",
      "xp_points" : 23
    },
    {
      "group" : "BUSINESS",
      "id" : "1090302025BUSD444",
      "last_updated" : "2025-11-08 17:20:00",
      "level" : "🔰 Newcomer",
      "name" : "KHADEZA AKTER",
      "xp_points" : 23
    },
    {
      "group" : "HUMANITIES",
      "id" : "1090302026HUMDHUMM67",
      "last_updated" : "2025-11-09 20:32:08",
      "level" : "🔰 Newcomer",
      "name" : "NYMA",
      "xp_points" : 23
    },
    {
      "group" : "SCIENCE",
      "id" : "1090302027SCID06",
      "last_updated" : "2025-11-24 23:28:30",
      "level" : "🔰 Newcomer",
      "name" : "GAZI MUNA",
      "xp_points" : 23
    },
    {
      "group" : "OTHERS",
      "id" : "1090302027366",
      "last_updated" : "2025-12-24 19:11:08",
      "level" : "🔰 Newcomer",
      "name" : "TRINA RANI SUTRADHAR",
      "xp_points" : 23
    },
    {
      "group" : "HUMANITIES",
      "id" : "1147432027HUMD017",
      "last_updated" : "2026-01-11 21:56:36",
      "level" : "🔰 Newcomer",
      "name" : "RAIMA HOSSAIN",
      "xp_points" : 23
    },
    {
      "group" : "HUMANITIES",
      "id" : "1090302026HUMD207049",
      "last_updated" : "2026-01-25 19:53:51",
      "level" : "🔰 Newcomer",
      "name" : "SURAIYA AFSANA",
      "xp_points" : 23
    },
    {
      "group" : "SCIENCE",
      "id" : "1090302027SCID159",
      "last_updated" : "2026-01-26 23:11:27",
      "level" : "🔰 Newcomer",
      "name" : "JANNATUL FERDOUS",
      "xp_points" : 23
    },
    {
      "group" : "SCIENCE",
      "id" : "1090302026SCIM355",
      "last_updated" : "2025-11-09 23:46:30",
      "level" : "🔰 Newcomer",
      "name" : "NADIA",
      "xp_points" : 22
    },
    {
      "group" : "HUMANITIES",
      "id" : "1090302027HUMDHUMM12",
      "last_updated" : "2025-11-12 21:18:52",
      "level" : "🔰 Newcomer",
      "name" : "HAMIDA AKTER KHUSI",
      "xp_points" : 22
    },
    {
      "group" : "BUSINESS",
      "id" : "1090302025BUSD236",
      "last_updated" : "2025-11-24 21:25:49",
      "level" : "🔰 Newcomer",
      "name" : "SUMAIYA AKTER",
      "xp_points" : 22
    },
    {
      "group" : "SCIENCE",
      "id" : "1082642027SCID26",
      "last_updated" : "2025-12-07 00:33:42",
      "level" : "🔰 Newcomer",
      "name" : "RAISA",
      "xp_points" : 22
    },
    {
      "group" : "SCIENCE",
      "id" : "1146792027SCID63",
      "last_updated" : "2026-02-01 20:25:35",
      "level" : "🔰 Newcomer",
      "name" : "JANNATUL TASNIM",
      "xp_points" : 22
    },
    {
      "group" : "HUMANITIES",
      "id" : "1090302027HUMD140",
      "last_updated" : "2025-10-30 19:05:51",
      "level" : "🔰 Newcomer",
      "name" : "MST MAYESHA RASHID",
      "xp_points" : 21
    },
    {
      "group" : "BUSINESS",
      "id" : "1090302026BUSD169",
      "last_updated" : "2025-11-07 20:25:21",
      "level" : "🔰 Newcomer",
      "name" : "MST. MASTURA MAHMUDA SADIA",
      "xp_points" : 21
    },
    {
      "group" : "HUMANITIES",
      "id" : "1090302026HUMD246",
      "last_updated" : "2025-11-08 13:42:42",
      "level" : "🔰 Newcomer",
      "name" : "RIMA AKTER SHAYMOLI",
      "xp_points" : 21
    },
    {
      "group" : "SCIENCE",
      "id" : "1085732026SCIM01",
      "last_updated" : "2025-11-09 22:00:11",
      "level" : "🔰 Newcomer",
      "name" : "MANY ",
      "xp_points" : 21
    },
    {
      "group" : "HUMANITIES",
      "id" : "1090302026HUMD276",
      "last_updated" : "2025-11-09 22:26:46",
      "level" : "🔰 Newcomer",
      "name" : "MST. SANJIDA RAHMAN",
      "xp_points" : 21
    },
    {
      "group" : "SCIENCE",
      "id" : "1090302026SCID60",
      "last_updated" : "2025-11-09 23:27:05",
      "level" : "🔰 Newcomer",
      "name" : "TAMANNA ",
      "xp_points" : 21
    },
    {
      "group" : "BUSINESS",
      "id" : "1042372027BUSD876457",
      "last_updated" : "2025-11-20 20:30:18",
      "level" : "🔰 Newcomer",
      "name" : "ASHRAFUL ALAM",
      "xp_points" : 21
    },
    {
      "group" : "SCIENCE",
      "id" : "1090302027SCID152",
      "last_updated" : "2025-11-25 07:02:26",
      "level" : "🔰 Newcomer",
      "name" : "JEBIN AFRIN",
      "xp_points" : 21
    },
    {
      "group" : "SCIENCE",
      "id" : "1090302027SCID257",
      "last_updated" : "2025-11-26 19:55:06",
      "level" : "🔰 Newcomer",
      "name" : "MITHILA AKTER",
      "xp_points" : 21
    },
    {
      "group" : "SCIENCE",
      "id" : "1146782026SCID1005",
      "last_updated" : "2025-10-28 21:18:10",
      "level" : "🔰 Newcomer",
      "name" : "NUSRAT JAHAN ORPA",
      "xp_points" : 20
    },
    {
      "group" : "HUMANITIES",
      "id" : "1090302026HUMD2",
      "last_updated" : "2025-11-04 17:54:17",
      "level" : "🔰 Newcomer",
      "name" : "JANNATUL ROJA GUNGUN",
      "xp_points" : 20
    },
    {
      "group" : "SCIENCE",
      "id" : "1090302027SCIM34",
      "last_updated" : "2025-11-24 22:20:37",
      "level" : "🔰 Newcomer",
      "name" : "AFRA SAIARA MINHA",
      "xp_points" : 20
    },
    {
      "group" : "BUSINESS",
      "id" : "1090302027BUSD180",
      "last_updated" : "2025-11-25 07:30:43",
      "level" : "🔰 Newcomer",
      "name" : "MOST. AFRIN SULTANA TITHEE",
      "xp_points" : 20
    },
    {
      "group" : "HUMANITIES",
      "id" : "1146782026HUMM1107",
      "last_updated" : "2025-12-13 14:22:46",
      "level" : "🔰 Newcomer",
      "name" : "SHANTA AKTAR",
      "xp_points" : 20
    },
    {
      "group" : "BUSINESS",
      "id" : "1090302025BUSD22",
      "last_updated" : "2025-11-03 19:45:54",
      "level" : "🔰 Newcomer",
      "name" : "SAMIYA AKTER",
      "xp_points" : 18
    },
    {
      "group" : "BUSINESS",
      "id" : "1090302026BUSD147",
      "last_updated" : "2025-11-06 20:22:57",
      "level" : "🔰 Newcomer",
      "name" : "PRITHA SAHA ",
      "xp_points" : 17
    },
    {
      "group" : "HUMANITIES",
      "id" : "1147432026HUMD226",
      "last_updated" : "2025-10-28 15:02:24",
      "level" : "🔰 Newcomer",
      "name" : "MARIA AKTER",
      "xp_points" : 16
    },
    {
      "group" : "BUSINESS",
      "id" : "1090302026BUSM159",
      "last_updated" : "2025-11-10 15:18:22",
      "level" : "🔰 Newcomer",
      "name" : "TAHMINA",
      "xp_points" : 15
    },
    {
      "group" : "BUSINESS",
      "id" : "1090302027BUSD319",
      "last_updated" : "2025-11-24 10:27:12",
      "level" : "🔰 Newcomer",
      "name" : "MIMYEA ISLAM MEGHLA",
      "xp_points" : 14
    },
    {
      "group" : "SCIENCE",
      "id" : "1090302026SCID11",
      "last_updated" : "2025-11-02 19:11:23",
      "level" : "🔰 Newcomer",
      "name" : "FATEMA JANNAT",
      "xp_points" : 13
    },
    {
      "group" : "HUMANITIES",
      "id" : "1146782026HUMD1163",
      "last_updated" : "2025-10-27 15:55:26",
      "level" : "🔰 Newcomer",
      "name" : "SUMAIYA AKTER",
      "xp_points" : 12
    },
    {
      "group" : "SCIENCE",
      "id" : "1090302027SCID101",
      "last_updated" : "2025-10-24 10:31:07",
      "level" : "🔰 Newcomer",
      "name" : "SUMI ",
      "xp_points" : 11
    },
    {
      "group" : "HUMANITIES",
      "id" : "1146782026HUMD527",
      "last_updated" : "2025-10-27 15:53:44",
      "level" : "🔰 Newcomer",
      "name" : "CHOITUS527@GMAIL.COM",
      "xp_points" : 11
    },
    {
      "group" : "BUSINESS",
      "id" : "1090302027BUSD442",
      "last_updated" : "2025-10-29 14:45:39",
      "level" : "🔰 Newcomer",
      "name" : "EMA AKTER",
      "xp_points" : 11
    },
    {
      "group" : "SCIENCE",
      "id" : "1146782026SCID101",
      "last_updated" : "2025-10-30 15:35:06",
      "level" : "🔰 Newcomer",
      "name" : "AFNAN AMIN",
      "xp_points" : 11
    },
    {
      "group" : "HUMANITIES",
      "id" : "1090302027HUMD129",
      "last_updated" : "2025-10-30 18:24:06",
      "level" : "🔰 Newcomer",
      "name" : "NUSRAT JAHAN KHUSBU",
      "xp_points" : 11
    },
    {
      "group" : "SCIENCE",
      "id" : "1090302027SCID125",
      "last_updated" : "2025-11-06 18:15:23",
      "level" : "🔰 Newcomer",
      "name" : "TASMIM SHAHIN KABBO",
      "xp_points" : 11
    },
    {
      "group" : "BUSINESS",
      "id" : "1090302026BUSM252",
      "last_updated" : "2025-11-05 12:54:25",
      "level" : "🔰 Newcomer",
      "name" : "SADIA AKTER",
      "xp_points" : 10
    },
    {
      "group" : "BUSINESS",
      "id" : "1090302026BUSD348",
      "last_updated" : "2025-11-07 07:56:48",
      "level" : "🔰 Newcomer",
      "name" : "MITHILA AKTER",
      "xp_points" : 10
    },
    {
      "group" : "HUMANITIES",
      "id" : "1090302027HUMD106069",
      "last_updated" : "2025-10-30 20:24:56",
      "level" : "🔰 Newcomer",
      "name" : "JANNATUL MAWA",
      "xp_points" : 9
    },
    {
      "group" : "HUMANITIES",
      "id" : "1090302027HUMD129",
      "last_updated" : "2025-11-20 22:28:14",
      "level" : "🔰 Newcomer",
      "name" : "NUSRAT JAHAN KHUSBU",
      "xp_points" : 9
    },
    {
      "group" : "BUSINESS",
      "id" : "1090302027BUSM166",
      "last_updated" : "2025-11-23 18:51:57",
      "level" : "🔰 Newcomer",
      "name" : "MAHUYA FERDOUSI ZIM",
      "xp_points" : 9
    },
    {
      "group" : "BUSINESS",
      "id" : "1090302026BUSM173",
      "last_updated" : "2025-11-08 17:21:55",
      "level" : "🔰 Newcomer",
      "name" : "AFSARA JANNAT",
      "xp_points" : 8
    },
    {
      "group" : "HUMANITIES",
      "id" : "2454245202HUMD7HUMD385365",
      "last_updated" : "2025-12-07 14:25:58",
      "level" : "🔰 Newcomer",
      "name" : "MD SHAKIB ",
      "xp_points" : 8
    },
    {
      "group" : "SCIENCE",
      "id" : "1090302025SCIM207",
      "last_updated" : "2025-11-08 05:40:06",
      "level" : "🔰 Newcomer",
      "name" : "TASNOVA TANJIM MITUL ",
      "xp_points" : 7
    },
    {
      "group" : "BUSINESS",
      "id" : "1090302025BUSD412",
      "last_updated" : "2025-11-02 09:12:59",
      "level" : "🔰 Newcomer",
      "name" : "IKSHER AKTER EMU ",
      "xp_points" : 5
    },
    {
      "group" : "HUMANITIES",
      "id" : "1090302027HUMD21",
      "last_updated" : "2025-11-24 23:41:12",
      "level" : "🔰 Newcomer",
      "name" : "MST. THAMINA YESMIN",
      "xp_points" : 3
    },
    {
      "group" : "BUSINESS",
      "id" : "1090302026BUSD270",
      "last_updated" : "2025-11-06 19:34:09",
      "level" : "🔰 Newcomer",
      "name" : "CHADNI",
      "xp_points" : 2
    },
    {
      "group" : "SCIENCE",
      "id" : "1090302027SCID114",
      "last_updated" : "2025-11-11 21:16:27",
      "level" : "🔰 Newcomer",
      "name" : "ZINIA ISLAM",
      "xp_points" : 2
    },
    {
      "group" : "BUSINESS",
      "id" : "1090302025BUSD410",
      "last_updated" : "2025-11-05 17:26:09",
      "level" : "🔰 Newcomer",
      "name" : "RIJUANA RITU",
      "xp_points" : 1
    },
    {
      "group" : "BUSINESS",
      "id" : "1090302026BUSD298",
      "last_updated" : "2025-11-06 19:42:35",
      "level" : "🔰 Newcomer",
      "name" : "JANNATUL MAWA MIRA",
      "xp_points" : 1
    },
    {
      "group" : "HUMANITIES",
      "id" : "1090302026HUMD260",
      "last_updated" : "2025-11-08 17:54:06",
      "level" : "🔰 Newcomer",
      "name" : "KASHFIA",
      "xp_points" : 1
    },
    {
      "group" : "BUSINESS",
      "id" : "1090302027BUSD245",
      "last_updated" : "2025-11-24 21:01:03",
      "level" : "🔰 Newcomer",
      "name" : "TANJILAKTER TONIMA",
      "xp_points" : 1
    },
    {
      "group" : "HUMANITIES",
      "id" : "1090302027HUMD180",
      "last_updated" : "2025-11-25 15:57:33",
      "level" : "🔰 Newcomer",
      "name" : "AFSANA AKTET AKHI",
      "xp_points" : 1
    },
    {
      "group" : "SCIENCE",
      "id" : "1090302025SCID3",
      "last_updated" : "2026-02-14T17:22:42Z",
      "level" : "🔰 Newcomer",
      "name" : "SHIBBIR",
      "xp_points" : 6
    }
  ]
}